hdlmake/__init__.py
hdlmake/__main__.py
hdlmake/_version.py
hdlmake/main.py
hdlmake/action/__init__.py
hdlmake/action/action.py
hdlmake/action/commands.py
hdlmake/action/gen_edalize.py
hdlmake/action/tree.py
hdlmake/fetch/__init__.py
hdlmake/fetch/fetcher.py
hdlmake/fetch/git.py
hdlmake/fetch/local.py
hdlmake/fetch/svn.py
hdlmake/manifest_parser/__init__.py
hdlmake/manifest_parser/configparser.py
hdlmake/manifest_parser/manifestparser.py
hdlmake/module/__init__.py
hdlmake/module/module.py
hdlmake/sourcefiles/__init__.py
hdlmake/sourcefiles/altera_libs.py
hdlmake/sourcefiles/bd_parser.py
hdlmake/sourcefiles/cxf_parser.py
hdlmake/sourcefiles/dep_file.py
hdlmake/sourcefiles/new_dep_solver.py
hdlmake/sourcefiles/sourcefileset.py
hdlmake/sourcefiles/srcfile.py
hdlmake/sourcefiles/systemlibs.py
hdlmake/sourcefiles/vhdl_parser.py
hdlmake/sourcefiles/vlog_parser.py
hdlmake/sourcefiles/xci_parser.py
hdlmake/tools/__init__.py
hdlmake/tools/active_hdl.py
hdlmake/tools/diamond.py
hdlmake/tools/ghdl.py
hdlmake/tools/ghdl_syn.py
hdlmake/tools/gowin.py
hdlmake/tools/icestorm.py
hdlmake/tools/ise.py
hdlmake/tools/isim.py
hdlmake/tools/iverilog.py
hdlmake/tools/libero.py
hdlmake/tools/liberosoc.py
hdlmake/tools/load_tool.py
hdlmake/tools/makefile.py
hdlmake/tools/makefilesim.py
hdlmake/tools/makefilesyn.py
hdlmake/tools/makefilevsim.py
hdlmake/tools/modelsim.py
hdlmake/tools/nvc.py
hdlmake/tools/planahead.py
hdlmake/tools/quartus.py
hdlmake/tools/riviera.py
hdlmake/tools/vivado.py
hdlmake/tools/vivado_sim.py
hdlmake/tools/vunit.py
hdlmake/tools/xilinx.py
hdlmake/tools/xilinx_prj.py
hdlmake/util/__init__.py
hdlmake/util/path.py
hdlmake/util/shell.py
hdlmake/util/termcolor.py
hdlmake-4.0.dist-info/licenses/COPYING
hdlmake-4.0.dist-info/METADATA
hdlmake-4.0.dist-info/WHEEL
hdlmake-4.0.dist-info/entry_points.txt
hdlmake-4.0.dist-info/top_level.txt
hdlmake-4.0.dist-info/RECORD
