Metadata-Version: 2.4
Name: hdlmake
Version: 4.0
Summary: Hdlmake generates multi-purpose makefiles for HDL projects management.
Home-page: https://gitlab.com/ohwr/project/hdl-make
Author: Javier D. Garcia-Lasheras, CERN
License: GPLv3
Classifier: Development Status :: 5 - Production/Stable
Classifier: Environment :: Console
Classifier: Topic :: Utilities
Classifier: License :: OSI Approved :: GNU General Public License v3 (GPLv3)
Classifier: Topic :: Software Development :: Build Tools
License-File: COPYING
Dynamic: author
Dynamic: classifier
Dynamic: description
Dynamic: description-content-type
Dynamic: home-page
Dynamic: license
Dynamic: license-file
Dynamic: summary
